config_py/__init__.py
configpy_file-1.0.dist-info/METADATA
configpy_file-1.0.dist-info/WHEEL
configpy_file-1.0.dist-info/top_level.txt
configpy_file-1.0.dist-info/RECORD
