Metadata-Version: 2.1
Name: configpy-file
Version: 1.0
Summary: Create config.py or config.h file
Home-page: UNKNOWN
Author: Vadim Simakin
Author-email: sima.vad@yandex.com
License: UNKNOWN
Platform: UNKNOWN
Classifier: Programming Language :: Python :: 3
Classifier: Operating System :: OS Independent
Requires-Python: >=3.7
